Workbook

Sheet Assumptions
A1: Key Assumptions
A2: Growth Rate (MoM) | B2: 0.15
A3: Churn Rate (Monthly) | B3: 0.02
A4: CAC (Customer Acquisition Cost) | B4: 5000
A5: LTV (Customer Lifetime Value) | B5: 45000
A6: Gross Margin % | B6: 0.72
A7: Monthly Burn Rate (INR) | B7: 1500000
A8: Starting Cash (INR) | B8: 15000000
A9: Tax Rate | B9: 0.25
A10: Conversion Rate | B10: 0.035
A11: Average Revenue Per User (USD) | B11: 29.99
A12: Price (INR/month) | B12: 999
A13: Discount Rate | B13: 0.12
... A15: Headcount Growth Rate (Annual) | B15: 0.5

Sheet P&L
A1: Profit & Loss Statement
B2: Month 1 | C2: Month 2 | D2: Month 3 | E2: Month 4 | F2: Month 5 | G2: Month 6
A3: Revenue | B3: 500000 | C3: =B3*(1+Assumptions!B2) | D3: =C3*(1+Assumptions!B2) | E3: =D3*(1+Assumptions!B2) | F3: 800000 | G3: =F3*(1+Assumptions!B2)
A4: COGS | B4: =B3*(1-Assumptions!B6) | C4: =C3*(1-Assumptions!B6) | D4: =D3*(1-Assumptions!B6) | E4: =E3*(1-Assumptions!B6) | F4: =F3*(1-Assumptions!B6) | G4: =G3*(1-Assumptions!B6)
A5: Gross Profit | B5: =B3-B4 | C5: =C3-C4 | D5: =D3-D4 | E5: =E3-E4 | F5: =F3-F4 | G5: =G3-G4
A6: Operating Expenses | B6: 400000 | C6: =B6*1.05 | D6: =C6*1.05 | E6: =D6*1.05 | F6: =E6*1.05 | G6: =F6*1.05
A7: Net Income | B7: =B5-B6 | C7: =C5-C6 | D7: =D5-D6 | E7: =E5-E6 | F7: =F5-F6 | G7: =G5-G6
A9: Total Revenue | B9: =SUM(B3:G3)

Sheet Cash Flow
A1: Cash Flow Statement | B1: Month 1 | C1: Month 2 | D1: Month 3
A2: Operating Cash Flow | B2: ='P&L'!B7 | C2: ='P&L'!C7 | D2: ='P&L'!D7
A3: CapEx | B3: -50000 | C3: -50000 | D3: -50000
A4: Net Cash Flow | B4: =B2+B3 | C4: =C2+C3 | D4: =D2+D3
A5: Ending Cash Balance | B5: =Assumptions!B8+B4 | C5: =B5+C4 | D5: =C5+D4
A7: Total Revenue | B7: 3200000
A9: Runway (months) | B9: =Assumptions!B8/Assumptions!B7

Sheet Balance Sheet
A1: Balance Sheet
A3: Total Assets | B3: 20000000
A5: Total Liabilities | B5: 8000000
A7: Total Equity | B7: 11000000

Sheet Cap Table
A1: Capitalization Table
A3: Shareholder | B3: Shares | C3: Ownership %
A4: Founder 1 | B4: 400000 | C4: 40
A5: Founder 2 | B5: 300000 | C5: 30
A6: Investor (Seed) | B6: 150000 | C6: 15
A7: ESOP/Option Pool | B7: 100000 | C7: 8
A8: Angel Investors | B8: 50000 | C8: 5
A10: Total | B10: =SUM(B4:B8) | C10: =SUM(C4:C8)
A12: Pre-Money Valuation (INR Cr) | B12: 10
A13: Investment Amount (INR Cr) | B13: 2
A14: Post-Money Valuation (INR Cr) | B14: =B12+B13

Sheet Revenue Model
A1: Revenue Forecast
A2: Users | B2: 1000 | C2: =B2*(1+Assumptions!B2) | D2: =C2*(1+Assumptions!B2)
A3: Revenue per User | B3: =Assumptions!B12 | C3: =Assumptions!B12 | D3: =Assumptions!B12
A4: Total Revenue | B4: =B2*B3 | C4: =C2*C3 | D4: =D2*D3
A5: MRR | B5: =B4 | C5: =C4 | D5: =D4
A6: ARR | B6: =B5*12 | C6: =C5*12 | D6: =D5*12
